authgw/__init__.py
authgw/admin.py
authgw/apps.py
authgw/models.py
authgw/tests.py
authgw/urls.py
authgw/views.py
authgw/migrations/__init__.py
authgw/templates/authgw/login.html
authgw/utils/__init__.py
authgw/utils/authenticators.py
authgw/utils/django.py
authgw/utils/ldap3.py
django_authgw-2.1.dist-info/LICENSE
django_authgw-2.1.dist-info/METADATA
django_authgw-2.1.dist-info/WHEEL
django_authgw-2.1.dist-info/top_level.txt
django_authgw-2.1.dist-info/RECORD
