Metadata-Version: 2.1
Name: django-authgw
Version: 2.1
Summary: Authentication gateway application for the Django framework
Home-page: http://github.com/sstacha/django-authgw
Author: Steve Stacha
Author-email: sstacha@gmail.com
License: MIT
Platform: UNKNOWN
Classifier: Development Status :: 3 - Alpha
Classifier: Programming Language :: Python :: 3
Classifier: License :: OSI Approved :: MIT License
Classifier: Operating System :: OS Independent
Classifier: Framework :: Django
Classifier: Framework :: Django :: 3.0
Classifier: Framework :: Django :: 4.0
Classifier: Topic :: System :: Systems Administration :: Authentication/Directory
Classifier: Topic :: Internet :: WWW/HTTP :: Site Management
Classifier: Topic :: Utilities
Requires-Python: >=3.8
Requires-Dist: django
Requires-Dist: ldap3
